example/__init__.py
example/dummy_balance.py
example/dummy_deck.py
example/dummy_pump.py
example/test.py
example/valve.py
sdl_webui/__init__.py
sdl_webui/app.py
sdl_webui/static/favicon.ico
sdl_webui/static/logo.png
sdl_webui/static/style.css
sdl_webui/static/gui_annotation/Slide1.png
sdl_webui/static/gui_annotation/Slide2.PNG
sdl_webui/static/gui_annotation/Slide3.PNG
sdl_webui/static/gui_annotation/installation_guide.PNG
sdl_webui/templates/base.html
sdl_webui/templates/controllers.html
sdl_webui/templates/controllers_home.html
sdl_webui/templates/controllers_new.html
sdl_webui/templates/experiment_builder.html
sdl_webui/templates/experiment_database.html
sdl_webui/templates/experiment_preview.html
sdl_webui/templates/experiment_run.html
sdl_webui/templates/grid.html
sdl_webui/templates/help.html
sdl_webui/templates/home.html
sdl_webui/templates/login.html
sdl_webui/templates/signup.html
sdl_webui-0.1.0.dist-info/LICENSE
sdl_webui-0.1.0.dist-info/METADATA
sdl_webui-0.1.0.dist-info/WHEEL
sdl_webui-0.1.0.dist-info/top_level.txt
sdl_webui-0.1.0.dist-info/RECORD
