Metadata-Version: 2.1
Name: sdl-webui
Version: 0.1.0
Summary: Design experiment on any Python-based SDLs.
Home-page: https://gitlab.com/heingroup/web_controller
Author: Ivory Zhang
Author-email: ivoryzhang@chem.ubc.ca
License: MIT
License-File: LICENSE
Requires-Dist: ax-platform
Requires-Dist: bcrypt
Requires-Dist: Flask-Login
Requires-Dist: Flask-Session
Requires-Dist: Flask-SocketIO
Requires-Dist: Flask-SQLAlchemy
Requires-Dist: mysqlclient ==2.1.1
Requires-Dist: SQLAlchemy-Utils
